pylaunches/__init__.py
pylaunches/api.py
pylaunches/common.py
pylaunches/const.py
pylaunches/exceptions.py
pylaunches/objects/__init__.py
pylaunches/objects/data.py
pylaunches/objects/event.py
pylaunches/objects/launch.py
pylaunches/objects/starship.py
pylaunches-1.4.0.dist-info/LICENSE
pylaunches-1.4.0.dist-info/METADATA
pylaunches-1.4.0.dist-info/WHEEL
pylaunches-1.4.0.dist-info/top_level.txt
pylaunches-1.4.0.dist-info/RECORD
