Metadata-Version: 2.1
Name: pylaunches
Version: 1.4.0
Home-page: https://github.com/ludeeus/pylaunches
Author: Joakim Sorensen
Author-email: hi@ludeeus.dev
Classifier: Programming Language :: Python :: 3
Classifier: License :: OSI Approved :: MIT License
Classifier: Operating System :: OS Independent
License-File: LICENSE
Requires-Dist: aiohttp
Requires-Dist: pytest-runner
